{"ocr_type": "receipts", "request_id": "P_113.11.77.230_ljr4697f_8qw", "ref_no": "oct_python_123", "file_name": "1.pdf", "request_received_on": 1688645907484, "success": true, "image_width": 1647, "image_height": 2330, "image_rotation": 0, "recognition_completed_on": 1688645908529, "receipts": [{"merchant_name": "sit amet eleifend pede libero quis orci.\nAddress Name", "merchant_address": "1147 Portage Pass, 9 Maple Drive", "merchant_phone": null, "merchant_website": null, "merchant_tax_reg_no": null, "merchant_company_reg_no": null, "region": null, "mall": null, "country": "US", "receipt_no": "OZ351148", "date": "1967-06-09", "time": null, "items": [{"amount": 16.0, "category": null, "description": "Spinach-Baby", "flags": "", "qty": null, "remarks": null, "tags": null, "unitPrice": null}, {"amount": 47.0, "category": null, "description": "Canadian Emmenthal", "flags": "", "qty": null, "remarks": null, "tags": null, "unitPrice": null}], "currency": "USD", "total": 63.0, "subtotal": null, "tax": null, "service_charge": null, "tip": null, "payment_method": null, "payment_details": null, "credit_card_type": null, "credit_card_number": null, "ocr_text": " INVOICE\n                                                               Invoice                   # INV-OZ351148\n                                                               Number\n                                                               Invoice Date                      6/9/1967\n Billing Information                                           Shipping Information\n Company                                                       Name\n Sed sagittis. Nam congue, risus semper                        Harald Rowantree\n porta volutpat, quam pede lobortis ligula,\n sit amet eleifend pede libero quis orci.                      Address\n Name                                                          1147 Portage Pass, 9 Maple Drive\n                                                               Bronx, New York, 10464\n Harald Rowantree                                              United States\n Address\n 1147 Portage Pass, 9 Maple Drive\n Bronx, New York, 10464\n United States\n Email\n igissing2@blogspot.com\n Products\n                                                                                                    Unit\n  Description                                    Quantity\n                                                                                                   Price\n  Spinach-Baby\n                                                 1                                                $16.00\n  $16.00\n  Canadian Emmenthal\n                                                 1                                                $47.00\n  $47.00\n                                            Total                                           $63.00\n Additional Notes                           Maecenas tincidunt lacus at velit. Vivamus vel nulla eget eros\n                                            elementum pellentesque.\n TERMS AND CONDITIONS\n 1. The Seller shall not be liable to the Buyer directly or indirectly for any loss or damage suffered by the Buyer.\n 2. The Seller warrants the product for one (1) year from the date of shipment.\n 3. Any purchase order received by the seller will be interpreted as accepting this offer and the sale offer in writing. The buyer may\n purchase the product in this offer only under the Terms and Conditions of the Seller included in this offer.\n Create your own automated PDFs with Jotform PDF Editor-It's free                               Jotform\n                                                                                            Remove Branding", "ocr_confidence": 98.7, "width": 1408, "height": 2200, "avg_char_width": 14.3224, "avg_line_height": 21.724, "conf_amount": 74, "source_locations": {"date": [[{"y": 251, "x": 1397}, {"y": 251, "x": 1522}, {"y": 278, "x": 1522}, {"y": 278, "x": 1397}]], "total": [[{"y": 1550, "x": 1330}, {"y": 1548, "x": 1505}, {"y": 1584, "x": 1505}, {"y": 1587, "x": 1330}]], "receipt_no": [[{"y": 140, "x": 1379}, {"y": 140, "x": 1523}, {"y": 162, "x": 1523}, {"y": 162, "x": 1379}]], "merchant_name": [[{"y": 646, "x": 123}, {"y": 643, "x": 215}, {"y": 667, "x": 215}, {"y": 667, "x": 123}]], "doc": [[{"y": -4, "x": 46}, {"y": -4, "x": 1595}, {"y": 2415, "x": 1595}, {"y": 2415, "x": 46}]], "merchant_address": [[{"y": 634, "x": 928}, {"y": 634, "x": 1399}, {"y": 659, "x": 1399}, {"y": 662, "x": 928}]]}}]}